{"mDataMap":{"1":{"f_id":1,"f_name":"新手超值礼包","f_Page":1,"f_type":1,"f_banner":1,"f_item_pic":0,"f_Price":"","f_PurchaseID":10,"f_ad":0,"f_free":0,"f_reward":"","f_limit_type":4,"f_limit_times":1,"f_discount":0,"f_extra_item":"","f_currency_icon":0,"f_sort":1,"f_appear_condition_type":0,"f_appear_condition_value":0,"f_hide":0},"2":{"f_id":2,"f_name":"天梯礼包1","f_Page":1,"f_type":1,"f_banner":2,"f_item_pic":0,"f_Price":"","f_PurchaseID":11,"f_ad":0,"f_free":0,"f_reward":"","f_limit_type":5,"f_limit_times":1,"f_discount":0,"f_extra_item":"","f_currency_icon":0,"f_sort":2,"f_appear_condition_type":1,"f_appear_condition_value":500,"f_hide":0},"3":{"f_id":3,"f_name":"紫金宝箱","f_Page":1,"f_type":2,"f_banner":0,"f_item_pic":4,"f_Price":"2-500","f_PurchaseID":0,"f_ad":0,"f_free":0,"f_reward":"94-1","f_limit_type":1,"f_limit_times":2,"f_discount":0,"f_extra_item":"","f_currency_icon":0,"f_sort":22,"f_appear_condition_type":0,"f_appear_condition_value":0,"f_hide":0},"4":{"f_id":4,"f_name":"星辰神话宝箱","f_Page":1,"f_type":2,"f_banner":0,"f_item_pic":5,"f_Price":"2-2000","f_PurchaseID":0,"f_ad":0,"f_free":0,"f_reward":"95-1","f_limit_type":1,"f_limit_times":1,"f_discount":0,"f_extra_item":"","f_currency_icon":0,"f_sort":23,"f_appear_condition_type":0,"f_appear_condition_value":0,"f_hide":0},"5":{"f_id":5,"f_name":"龙魂至尊宝箱","f_Page":1,"f_type":2,"f_banner":0,"f_item_pic":6,"f_Price":"2-3500","f_PurchaseID":0,"f_ad":0,"f_free":0,"f_reward":"96-1","f_limit_type":1,"f_limit_times":1,"f_discount":0,"f_extra_item":"","f_currency_icon":0,"f_sort":24,"f_appear_condition_type":0,"f_appear_condition_value":0,"f_hide":0},"6":{"f_id":6,"f_name":"免费灵香","f_Page":1,"f_type":3,"f_banner":0,"f_item_pic":1,"f_Price":"","f_PurchaseID":0,"f_ad":1,"f_free":0,"f_reward":"4-1","f_limit_type":1,"f_limit_times":1,"f_discount":10000,"f_extra_item":"","f_currency_icon":0,"f_sort":25,"f_appear_condition_type":0,"f_appear_condition_value":0,"f_hide":0},"7":{"f_id":7,"f_name":"日限购灵香","f_Page":1,"f_type":3,"f_banner":0,"f_item_pic":1,"f_Price":"2-50","f_PurchaseID":0,"f_ad":0,"f_free":0,"f_reward":"4-1","f_limit_type":1,"f_limit_times":30,"f_discount":5000,"f_extra_item":"","f_currency_icon":0,"f_sort":26,"f_appear_condition_type":0,"f_appear_condition_value":0,"f_hide":0},"8":{"f_id":8,"f_name":"周限购灵香","f_Page":1,"f_type":3,"f_banner":0,"f_item_pic":1,"f_Price":"2-80","f_PurchaseID":0,"f_ad":0,"f_free":0,"f_reward":"4-1","f_limit_type":2,"f_limit_times":50,"f_discount":2000,"f_extra_item":"","f_currency_icon":0,"f_sort":27,"f_appear_condition_type":0,"f_appear_condition_value":0,"f_hide":0},"9":{"f_id":9,"f_name":"每日特惠神魄","f_Page":1,"f_type":4,"f_banner":0,"f_item_pic":2,"f_Price":"2-50","f_PurchaseID":0,"f_ad":0,"f_free":0,"f_reward":"5-1","f_limit_type":1,"f_limit_times":5,"f_discount":4000,"f_extra_item":"","f_currency_icon":0,"f_sort":28,"f_appear_condition_type":0,"f_appear_condition_value":0,"f_hide":0},"10":{"f_id":10,"f_name":"每日神魄","f_Page":1,"f_type":4,"f_banner":0,"f_item_pic":2,"f_Price":"2-980","f_PurchaseID":0,"f_ad":0,"f_free":0,"f_reward":"5-20","f_limit_type":1,"f_limit_times":5,"f_discount":4000,"f_extra_item":"","f_currency_icon":0,"f_sort":29,"f_appear_condition_type":0,"f_appear_condition_value":0,"f_hide":0},"11":{"f_id":11,"f_name":"每周神魄","f_Page":1,"f_type":4,"f_banner":0,"f_item_pic":2,"f_Price":"2-2400","f_PurchaseID":0,"f_ad":0,"f_free":0,"f_reward":"5-50","f_limit_type":1,"f_limit_times":3,"f_discount":4000,"f_extra_item":"","f_currency_icon":0,"f_sort":30,"f_appear_condition_type":0,"f_appear_condition_value":0,"f_hide":0},"12":{"f_id":12,"f_name":"60灵玉","f_Page":2,"f_type":6,"f_banner":0,"f_item_pic":0,"f_Price":"","f_PurchaseID":1,"f_ad":0,"f_free":0,"f_reward":"","f_limit_type":0,"f_limit_times":0,"f_discount":0,"f_extra_item":"2-60","f_currency_icon":1,"f_sort":7,"f_appear_condition_type":0,"f_appear_condition_value":0,"f_hide":0},"13":{"f_id":13,"f_name":"300灵玉","f_Page":2,"f_type":6,"f_banner":0,"f_item_pic":0,"f_Price":"","f_PurchaseID":2,"f_ad":0,"f_free":0,"f_reward":"","f_limit_type":0,"f_limit_times":0,"f_discount":0,"f_extra_item":"2-300","f_currency_icon":2,"f_sort":8,"f_appear_condition_type":0,"f_appear_condition_value":0,"f_hide":0},"14":{"f_id":14,"f_name":"680灵玉","f_Page":2,"f_type":6,"f_banner":0,"f_item_pic":0,"f_Price":"","f_PurchaseID":3,"f_ad":0,"f_free":0,"f_reward":"","f_limit_type":0,"f_limit_times":0,"f_discount":0,"f_extra_item":"2-680","f_currency_icon":3,"f_sort":9,"f_appear_condition_type":0,"f_appear_condition_value":0,"f_hide":0},"15":{"f_id":15,"f_name":"1280灵玉","f_Page":2,"f_type":6,"f_banner":0,"f_item_pic":0,"f_Price":"","f_PurchaseID":4,"f_ad":0,"f_free":0,"f_reward":"","f_limit_type":0,"f_limit_times":0,"f_discount":0,"f_extra_item":"2-1280","f_currency_icon":4,"f_sort":10,"f_appear_condition_type":0,"f_appear_condition_value":0,"f_hide":0},"16":{"f_id":16,"f_name":"3280灵玉","f_Page":2,"f_type":6,"f_banner":0,"f_item_pic":0,"f_Price":"","f_PurchaseID":5,"f_ad":0,"f_free":0,"f_reward":"","f_limit_type":0,"f_limit_times":0,"f_discount":0,"f_extra_item":"2-3280","f_currency_icon":5,"f_sort":11,"f_appear_condition_type":0,"f_appear_condition_value":0,"f_hide":0},"17":{"f_id":17,"f_name":"6480灵玉","f_Page":2,"f_type":6,"f_banner":0,"f_item_pic":0,"f_Price":"","f_PurchaseID":6,"f_ad":0,"f_free":0,"f_reward":"","f_limit_type":0,"f_limit_times":0,"f_discount":0,"f_extra_item":"2-6480","f_currency_icon":6,"f_sort":12,"f_appear_condition_type":0,"f_appear_condition_value":0,"f_hide":0},"18":{"f_id":18,"f_name":"1000铜钱","f_Page":2,"f_type":7,"f_banner":0,"f_item_pic":0,"f_Price":"","f_PurchaseID":0,"f_ad":2,"f_free":1,"f_reward":"3-1000","f_limit_type":1,"f_limit_times":3,"f_discount":0,"f_extra_item":"","f_currency_icon":7,"f_sort":13,"f_appear_condition_type":0,"f_appear_condition_value":0,"f_hide":0},"19":{"f_id":19,"f_name":"10000铜钱","f_Page":2,"f_type":7,"f_banner":0,"f_item_pic":0,"f_Price":"2-100","f_PurchaseID":0,"f_ad":0,"f_free":0,"f_reward":"3-10000","f_limit_type":0,"f_limit_times":0,"f_discount":0,"f_extra_item":"","f_currency_icon":8,"f_sort":14,"f_appear_condition_type":0,"f_appear_condition_value":0,"f_hide":0},"20":{"f_id":20,"f_name":"31000铜钱","f_Page":2,"f_type":7,"f_banner":0,"f_item_pic":0,"f_Price":"2-300","f_PurchaseID":0,"f_ad":0,"f_free":0,"f_reward":"3-31000","f_limit_type":0,"f_limit_times":0,"f_discount":0,"f_extra_item":"","f_currency_icon":9,"f_sort":15,"f_appear_condition_type":0,"f_appear_condition_value":0,"f_hide":0},"21":{"f_id":21,"f_name":"55000铜钱","f_Page":2,"f_type":7,"f_banner":0,"f_item_pic":0,"f_Price":"2-500","f_PurchaseID":0,"f_ad":0,"f_free":0,"f_reward":"3-55000","f_limit_type":0,"f_limit_times":0,"f_discount":0,"f_extra_item":"","f_currency_icon":10,"f_sort":16,"f_appear_condition_type":0,"f_appear_condition_value":0,"f_hide":0},"22":{"f_id":22,"f_name":"120000铜钱","f_Page":2,"f_type":7,"f_banner":0,"f_item_pic":0,"f_Price":"2-1000","f_PurchaseID":0,"f_ad":0,"f_free":0,"f_reward":"3-120000","f_limit_type":0,"f_limit_times":0,"f_discount":0,"f_extra_item":"","f_currency_icon":11,"f_sort":17,"f_appear_condition_type":0,"f_appear_condition_value":0,"f_hide":0},"23":{"f_id":23,"f_name":"380000铜钱","f_Page":2,"f_type":7,"f_banner":0,"f_item_pic":0,"f_Price":"2-3000","f_PurchaseID":0,"f_ad":0,"f_free":0,"f_reward":"3-380000","f_limit_type":0,"f_limit_times":0,"f_discount":0,"f_extra_item":"","f_currency_icon":12,"f_sort":18,"f_appear_condition_type":0,"f_appear_condition_value":0,"f_hide":0},"24":{"f_id":24,"f_name":"经典卡包","f_Page":3,"f_type":8,"f_banner":1,"f_item_pic":0,"f_Price":"","f_PurchaseID":0,"f_ad":1,"f_free":0,"f_reward":"90-1","f_limit_type":1,"f_limit_times":1,"f_discount":0,"f_extra_item":"","f_currency_icon":1,"f_sort":1,"f_appear_condition_type":0,"f_appear_condition_value":0,"f_hide":0},"25":{"f_id":25,"f_name":"至臻卡包","f_Page":3,"f_type":8,"f_banner":2,"f_item_pic":0,"f_Price":"2-150","f_PurchaseID":0,"f_ad":0,"f_free":0,"f_reward":"89-1","f_limit_type":0,"f_limit_times":0,"f_discount":0,"f_extra_item":"","f_currency_icon":2,"f_sort":2,"f_appear_condition_type":0,"f_appear_condition_value":0,"f_hide":0},"26":{"f_id":26,"f_name":"赛季卡包","f_Page":3,"f_type":8,"f_banner":3,"f_item_pic":0,"f_Price":"2-150","f_PurchaseID":0,"f_ad":0,"f_free":0,"f_reward":"107-1","f_limit_type":1,"f_limit_times":50,"f_discount":0,"f_extra_item":"","f_currency_icon":3,"f_sort":3,"f_appear_condition_type":0,"f_appear_condition_value":0,"f_hide":0},"27":{"f_id":27,"f_name":"免费钻石","f_Page":2,"f_type":5,"f_banner":0,"f_item_pic":0,"f_Price":"","f_PurchaseID":0,"f_ad":2,"f_free":1,"f_reward":"2-10","f_limit_type":1,"f_limit_times":3,"f_discount":0,"f_extra_item":"","f_currency_icon":0,"f_sort":1,"f_appear_condition_type":0,"f_appear_condition_value":0,"f_hide":0},"28":{"f_id":28,"f_name":"热卖商品2","f_Page":2,"f_type":5,"f_banner":1,"f_item_pic":0,"f_Price":"","f_PurchaseID":0,"f_ad":0,"f_free":0,"f_reward":"","f_limit_type":0,"f_limit_times":0,"f_discount":0,"f_extra_item":"","f_currency_icon":0,"f_sort":2,"f_appear_condition_type":0,"f_appear_condition_value":0,"f_hide":0},"29":{"f_id":29,"f_name":"热卖商品3","f_Page":2,"f_type":5,"f_banner":2,"f_item_pic":0,"f_Price":"","f_PurchaseID":0,"f_ad":0,"f_free":0,"f_reward":"","f_limit_type":0,"f_limit_times":0,"f_discount":0,"f_extra_item":"","f_currency_icon":0,"f_sort":3,"f_appear_condition_type":0,"f_appear_condition_value":0,"f_hide":0},"30":{"f_id":30,"f_name":"热卖商品4","f_Page":2,"f_type":5,"f_banner":3,"f_item_pic":0,"f_Price":"","f_PurchaseID":0,"f_ad":0,"f_free":0,"f_reward":"","f_limit_type":0,"f_limit_times":0,"f_discount":0,"f_extra_item":"","f_currency_icon":0,"f_sort":4,"f_appear_condition_type":0,"f_appear_condition_value":0,"f_hide":0},"31":{"f_id":31,"f_name":"热卖商品5","f_Page":2,"f_type":5,"f_banner":4,"f_item_pic":0,"f_Price":"","f_PurchaseID":0,"f_ad":0,"f_free":0,"f_reward":"","f_limit_type":0,"f_limit_times":0,"f_discount":0,"f_extra_item":"","f_currency_icon":0,"f_sort":5,"f_appear_condition_type":0,"f_appear_condition_value":0,"f_hide":0},"32":{"f_id":32,"f_name":"热卖商品6","f_Page":2,"f_type":5,"f_banner":5,"f_item_pic":0,"f_Price":"","f_PurchaseID":0,"f_ad":0,"f_free":0,"f_reward":"","f_limit_type":0,"f_limit_times":0,"f_discount":0,"f_extra_item":"","f_currency_icon":0,"f_sort":6,"f_appear_condition_type":0,"f_appear_condition_value":0,"f_hide":0},"33":{"f_id":33,"f_name":"天梯礼包2","f_Page":1,"f_type":1,"f_banner":2,"f_item_pic":0,"f_Price":"","f_PurchaseID":16,"f_ad":0,"f_free":0,"f_reward":"","f_limit_type":5,"f_limit_times":1,"f_discount":0,"f_extra_item":"","f_currency_icon":0,"f_sort":3,"f_appear_condition_type":1,"f_appear_condition_value":1000,"f_hide":0},"34":{"f_id":34,"f_name":"天梯礼包3","f_Page":1,"f_type":1,"f_banner":2,"f_item_pic":0,"f_Price":"","f_PurchaseID":17,"f_ad":0,"f_free":0,"f_reward":"","f_limit_type":5,"f_limit_times":1,"f_discount":0,"f_extra_item":"","f_currency_icon":0,"f_sort":4,"f_appear_condition_type":1,"f_appear_condition_value":1500,"f_hide":0},"35":{"f_id":35,"f_name":"天梯礼包4","f_Page":1,"f_type":1,"f_banner":2,"f_item_pic":0,"f_Price":"","f_PurchaseID":18,"f_ad":0,"f_free":0,"f_reward":"","f_limit_type":5,"f_limit_times":1,"f_discount":0,"f_extra_item":"","f_currency_icon":0,"f_sort":5,"f_appear_condition_type":1,"f_appear_condition_value":2000,"f_hide":0},"36":{"f_id":36,"f_name":"天梯礼包5","f_Page":1,"f_type":1,"f_banner":2,"f_item_pic":0,"f_Price":"","f_PurchaseID":19,"f_ad":0,"f_free":0,"f_reward":"","f_limit_type":5,"f_limit_times":1,"f_discount":0,"f_extra_item":"","f_currency_icon":0,"f_sort":6,"f_appear_condition_type":1,"f_appear_condition_value":2500,"f_hide":0},"37":{"f_id":37,"f_name":"天梯礼包6","f_Page":1,"f_type":1,"f_banner":2,"f_item_pic":0,"f_Price":"","f_PurchaseID":20,"f_ad":0,"f_free":0,"f_reward":"","f_limit_type":5,"f_limit_times":1,"f_discount":0,"f_extra_item":"","f_currency_icon":0,"f_sort":7,"f_appear_condition_type":1,"f_appear_condition_value":3000,"f_hide":0},"38":{"f_id":38,"f_name":"天梯礼包7","f_Page":1,"f_type":1,"f_banner":2,"f_item_pic":0,"f_Price":"","f_PurchaseID":21,"f_ad":0,"f_free":0,"f_reward":"","f_limit_type":5,"f_limit_times":1,"f_discount":0,"f_extra_item":"","f_currency_icon":0,"f_sort":8,"f_appear_condition_type":1,"f_appear_condition_value":3500,"f_hide":0},"39":{"f_id":39,"f_name":"天梯礼包8","f_Page":1,"f_type":1,"f_banner":2,"f_item_pic":0,"f_Price":"","f_PurchaseID":22,"f_ad":0,"f_free":0,"f_reward":"","f_limit_type":5,"f_limit_times":1,"f_discount":0,"f_extra_item":"","f_currency_icon":0,"f_sort":9,"f_appear_condition_type":1,"f_appear_condition_value":4000,"f_hide":0},"40":{"f_id":40,"f_name":"天梯礼包9","f_Page":1,"f_type":1,"f_banner":2,"f_item_pic":0,"f_Price":"","f_PurchaseID":23,"f_ad":0,"f_free":0,"f_reward":"","f_limit_type":5,"f_limit_times":1,"f_discount":0,"f_extra_item":"","f_currency_icon":0,"f_sort":10,"f_appear_condition_type":1,"f_appear_condition_value":4500,"f_hide":0},"41":{"f_id":41,"f_name":"天梯礼包10","f_Page":1,"f_type":1,"f_banner":2,"f_item_pic":0,"f_Price":"","f_PurchaseID":24,"f_ad":0,"f_free":0,"f_reward":"","f_limit_type":5,"f_limit_times":1,"f_discount":0,"f_extra_item":"","f_currency_icon":0,"f_sort":11,"f_appear_condition_type":1,"f_appear_condition_value":5000,"f_hide":0},"42":{"f_id":42,"f_name":"天梯礼包11","f_Page":1,"f_type":1,"f_banner":2,"f_item_pic":0,"f_Price":"","f_PurchaseID":25,"f_ad":0,"f_free":0,"f_reward":"","f_limit_type":5,"f_limit_times":1,"f_discount":0,"f_extra_item":"","f_currency_icon":0,"f_sort":12,"f_appear_condition_type":1,"f_appear_condition_value":5500,"f_hide":0},"43":{"f_id":43,"f_name":"天梯礼包12","f_Page":1,"f_type":1,"f_banner":2,"f_item_pic":0,"f_Price":"","f_PurchaseID":26,"f_ad":0,"f_free":0,"f_reward":"","f_limit_type":5,"f_limit_times":1,"f_discount":0,"f_extra_item":"","f_currency_icon":0,"f_sort":13,"f_appear_condition_type":1,"f_appear_condition_value":6000,"f_hide":0},"44":{"f_id":44,"f_name":"天梯礼包13","f_Page":1,"f_type":1,"f_banner":2,"f_item_pic":0,"f_Price":"","f_PurchaseID":27,"f_ad":0,"f_free":0,"f_reward":"","f_limit_type":5,"f_limit_times":1,"f_discount":0,"f_extra_item":"","f_currency_icon":0,"f_sort":14,"f_appear_condition_type":1,"f_appear_condition_value":6500,"f_hide":0},"45":{"f_id":45,"f_name":"天梯礼包14","f_Page":1,"f_type":1,"f_banner":2,"f_item_pic":0,"f_Price":"","f_PurchaseID":28,"f_ad":0,"f_free":0,"f_reward":"","f_limit_type":5,"f_limit_times":1,"f_discount":0,"f_extra_item":"","f_currency_icon":0,"f_sort":15,"f_appear_condition_type":1,"f_appear_condition_value":7000,"f_hide":0},"46":{"f_id":46,"f_name":"天梯礼包15","f_Page":1,"f_type":1,"f_banner":2,"f_item_pic":0,"f_Price":"","f_PurchaseID":29,"f_ad":0,"f_free":0,"f_reward":"","f_limit_type":5,"f_limit_times":1,"f_discount":0,"f_extra_item":"","f_currency_icon":0,"f_sort":16,"f_appear_condition_type":1,"f_appear_condition_value":7500,"f_hide":0},"47":{"f_id":47,"f_name":"天梯礼包16","f_Page":1,"f_type":1,"f_banner":2,"f_item_pic":0,"f_Price":"","f_PurchaseID":30,"f_ad":0,"f_free":0,"f_reward":"","f_limit_type":5,"f_limit_times":1,"f_discount":0,"f_extra_item":"","f_currency_icon":0,"f_sort":17,"f_appear_condition_type":1,"f_appear_condition_value":8000,"f_hide":0},"48":{"f_id":48,"f_name":"天梯礼包17","f_Page":1,"f_type":1,"f_banner":2,"f_item_pic":0,"f_Price":"","f_PurchaseID":31,"f_ad":0,"f_free":0,"f_reward":"","f_limit_type":5,"f_limit_times":1,"f_discount":0,"f_extra_item":"","f_currency_icon":0,"f_sort":18,"f_appear_condition_type":1,"f_appear_condition_value":8500,"f_hide":0},"49":{"f_id":49,"f_name":"天梯礼包18","f_Page":1,"f_type":1,"f_banner":2,"f_item_pic":0,"f_Price":"","f_PurchaseID":32,"f_ad":0,"f_free":0,"f_reward":"","f_limit_type":5,"f_limit_times":1,"f_discount":0,"f_extra_item":"","f_currency_icon":0,"f_sort":19,"f_appear_condition_type":1,"f_appear_condition_value":9000,"f_hide":0},"50":{"f_id":50,"f_name":"天梯礼包19","f_Page":1,"f_type":1,"f_banner":2,"f_item_pic":0,"f_Price":"","f_PurchaseID":33,"f_ad":0,"f_free":0,"f_reward":"","f_limit_type":5,"f_limit_times":1,"f_discount":0,"f_extra_item":"","f_currency_icon":0,"f_sort":20,"f_appear_condition_type":1,"f_appear_condition_value":9500,"f_hide":0},"51":{"f_id":51,"f_name":"天梯礼包20","f_Page":1,"f_type":1,"f_banner":2,"f_item_pic":0,"f_Price":"","f_PurchaseID":34,"f_ad":0,"f_free":0,"f_reward":"","f_limit_type":5,"f_limit_times":1,"f_discount":0,"f_extra_item":"","f_currency_icon":0,"f_sort":21,"f_appear_condition_type":1,"f_appear_condition_value":10000,"f_hide":0},"52":{"f_id":52,"f_name":"突围战灵玉","f_Page":4,"f_type":9,"f_banner":0,"f_item_pic":0,"f_Price":"127-200","f_PurchaseID":0,"f_ad":0,"f_free":0,"f_reward":"2-30","f_limit_type":1,"f_limit_times":8,"f_discount":0,"f_extra_item":"","f_currency_icon":0,"f_sort":6,"f_appear_condition_type":0,"f_appear_condition_value":0,"f_hide":0},"53":{"f_id":53,"f_name":"突围战铜钱","f_Page":4,"f_type":9,"f_banner":0,"f_item_pic":0,"f_Price":"127-130","f_PurchaseID":0,"f_ad":0,"f_free":0,"f_reward":"3-2000","f_limit_type":1,"f_limit_times":3,"f_discount":0,"f_extra_item":"","f_currency_icon":0,"f_sort":14,"f_appear_condition_type":0,"f_appear_condition_value":0,"f_hide":0},"54":{"f_id":54,"f_name":"突围战铜钱","f_Page":4,"f_type":9,"f_banner":0,"f_item_pic":0,"f_Price":"127-410","f_PurchaseID":0,"f_ad":0,"f_free":0,"f_reward":"3-5000","f_limit_type":1,"f_limit_times":3,"f_discount":0,"f_extra_item":"","f_currency_icon":0,"f_sort":15,"f_appear_condition_type":0,"f_appear_condition_value":0,"f_hide":0},"55":{"f_id":55,"f_name":"突围战时光沙漏","f_Page":4,"f_type":9,"f_banner":0,"f_item_pic":0,"f_Price":"127-150","f_PurchaseID":0,"f_ad":0,"f_free":0,"f_reward":"88-1","f_limit_type":1,"f_limit_times":10,"f_discount":0,"f_extra_item":"","f_currency_icon":0,"f_sort":11,"f_appear_condition_type":0,"f_appear_condition_value":0,"f_hide":1},"56":{"f_id":56,"f_name":"突围战灵香","f_Page":4,"f_type":9,"f_banner":0,"f_item_pic":0,"f_Price":"127-400","f_PurchaseID":0,"f_ad":0,"f_free":0,"f_reward":"4-1","f_limit_type":1,"f_limit_times":2,"f_discount":0,"f_extra_item":"","f_currency_icon":0,"f_sort":9,"f_appear_condition_type":0,"f_appear_condition_value":0,"f_hide":0},"57":{"f_id":57,"f_name":"突围战灵香","f_Page":4,"f_type":9,"f_banner":0,"f_item_pic":0,"f_Price":"127-600","f_PurchaseID":0,"f_ad":0,"f_free":0,"f_reward":"4-1","f_limit_type":1,"f_limit_times":4,"f_discount":0,"f_extra_item":"","f_currency_icon":0,"f_sort":10,"f_appear_condition_type":0,"f_appear_condition_value":0,"f_hide":0},"58":{"f_id":58,"f_name":"突围战高级卡包","f_Page":4,"f_type":9,"f_banner":0,"f_item_pic":0,"f_Price":"127-1000","f_PurchaseID":0,"f_ad":0,"f_free":0,"f_reward":"89-1","f_limit_type":1,"f_limit_times":5,"f_discount":0,"f_extra_item":"","f_currency_icon":0,"f_sort":7,"f_appear_condition_type":0,"f_appear_condition_value":0,"f_hide":0},"59":{"f_id":59,"f_name":"突围战普通卡包","f_Page":4,"f_type":9,"f_banner":0,"f_item_pic":0,"f_Price":"127-300","f_PurchaseID":0,"f_ad":0,"f_free":0,"f_reward":"90-1","f_limit_type":1,"f_limit_times":99,"f_discount":0,"f_extra_item":"","f_currency_icon":0,"f_sort":13,"f_appear_condition_type":0,"f_appear_condition_value":0,"f_hide":0},"60":{"f_id":60,"f_name":"大鹏鸟头像","f_Page":4,"f_type":9,"f_banner":0,"f_item_pic":0,"f_Price":"127-2000","f_PurchaseID":0,"f_ad":0,"f_free":0,"f_reward":"116-1","f_limit_type":4,"f_limit_times":1,"f_discount":0,"f_extra_item":"","f_currency_icon":0,"f_sort":1,"f_appear_condition_type":0,"f_appear_condition_value":0,"f_hide":0},"61":{"f_id":61,"f_name":"嫦娥头像","f_Page":4,"f_type":9,"f_banner":0,"f_item_pic":0,"f_Price":"127-2000","f_PurchaseID":0,"f_ad":0,"f_free":0,"f_reward":"115-1","f_limit_type":4,"f_limit_times":1,"f_discount":0,"f_extra_item":"","f_currency_icon":0,"f_sort":2,"f_appear_condition_type":0,"f_appear_condition_value":0,"f_hide":0},"62":{"f_id":62,"f_name":"九尾灵狐头像","f_Page":4,"f_type":9,"f_banner":0,"f_item_pic":0,"f_Price":"127-8888","f_PurchaseID":0,"f_ad":0,"f_free":0,"f_reward":"117-1","f_limit_type":4,"f_limit_times":1,"f_discount":0,"f_extra_item":"","f_currency_icon":0,"f_sort":3,"f_appear_condition_type":0,"f_appear_condition_value":0,"f_hide":0},"63":{"f_id":63,"f_name":"蚩尤头像","f_Page":4,"f_type":9,"f_banner":0,"f_item_pic":0,"f_Price":"127-8888","f_PurchaseID":0,"f_ad":0,"f_free":0,"f_reward":"118-1","f_limit_type":4,"f_limit_times":1,"f_discount":0,"f_extra_item":"","f_currency_icon":0,"f_sort":4,"f_appear_condition_type":0,"f_appear_condition_value":0,"f_hide":0},"64":{"f_id":64,"f_name":"头像框-悦动盛典","f_Page":4,"f_type":9,"f_banner":0,"f_item_pic":0,"f_Price":"127-30000","f_PurchaseID":0,"f_ad":0,"f_free":0,"f_reward":"121-1","f_limit_type":4,"f_limit_times":1,"f_discount":0,"f_extra_item":"","f_currency_icon":0,"f_sort":5,"f_appear_condition_type":0,"f_appear_condition_value":0,"f_hide":0},"65":{"f_id":65,"f_name":"突围战时光沙漏","f_Page":4,"f_type":9,"f_banner":0,"f_item_pic":0,"f_Price":"127-260","f_PurchaseID":0,"f_ad":0,"f_free":0,"f_reward":"88-1","f_limit_type":1,"f_limit_times":30,"f_discount":0,"f_extra_item":"","f_currency_icon":0,"f_sort":12,"f_appear_condition_type":0,"f_appear_condition_value":0,"f_hide":1},"66":{"f_id":66,"f_name":"突围战抽奖券","f_Page":4,"f_type":9,"f_banner":0,"f_item_pic":0,"f_Price":"127-1000","f_PurchaseID":0,"f_ad":0,"f_free":0,"f_reward":"174-30","f_limit_type":1,"f_limit_times":8,"f_discount":0,"f_extra_item":"","f_currency_icon":0,"f_sort":8,"f_appear_condition_type":0,"f_appear_condition_value":0,"f_hide":0},"67":{"f_id":67,"f_name":"突围战困难抽奖券","f_Page":4,"f_type":9,"f_banner":0,"f_item_pic":0,"f_Price":"180-5","f_PurchaseID":0,"f_ad":0,"f_free":0,"f_reward":"5-1","f_limit_type":1,"f_limit_times":3,"f_discount":0,"f_extra_item":"","f_currency_icon":0,"f_sort":16,"f_appear_condition_type":0,"f_appear_condition_value":0,"f_hide":0},"68":{"f_id":68,"f_name":"突围战困难5级宝箱","f_Page":4,"f_type":9,"f_banner":0,"f_item_pic":0,"f_Price":"180-120","f_PurchaseID":0,"f_ad":0,"f_free":0,"f_reward":"95-1","f_limit_type":3,"f_limit_times":1,"f_discount":0,"f_extra_item":"","f_currency_icon":0,"f_sort":17,"f_appear_condition_type":0,"f_appear_condition_value":0,"f_hide":0},"69":{"f_id":69,"f_name":"突围战困难灵香","f_Page":4,"f_type":9,"f_banner":0,"f_item_pic":0,"f_Price":"180-5","f_PurchaseID":0,"f_ad":0,"f_free":0,"f_reward":"4-1","f_limit_type":1,"f_limit_times":3,"f_discount":0,"f_extra_item":"","f_currency_icon":0,"f_sort":18,"f_appear_condition_type":0,"f_appear_condition_value":0,"f_hide":0}}}